pyfisher/__init__.py
pyfisher/_version.py
pyfisher/mpi.py
pyfisher/pyfisher.py
pyfisher/data/lensing_nl/planck_2018_mv_nlkk.dat
pyfisher/data/lensing_nl/s4_noise.dat
pyfisher/data/lensing_nl/so_v3_1_deproj0_goal_fsky0p4_it.dat
pyfisher/data/v20201120_boss_bao/params.txt
pyfisher/data/v20201120_boss_bao/v20201120_boss_bao_bao_H0_d.txt
pyfisher/data/v20201120_boss_bao/v20201120_boss_bao_bao_H0_u.txt
pyfisher/data/v20201120_boss_bao/v20201120_boss_bao_bao_fiducial.txt
pyfisher/data/v20201120_boss_bao/v20201120_boss_bao_bao_fisher.txt
pyfisher/data/v20201120_boss_bao/v20201120_boss_bao_bao_mnu_d.txt
pyfisher/data/v20201120_boss_bao/v20201120_boss_bao_bao_mnu_u.txt
pyfisher/data/v20201120_boss_bao/v20201120_boss_bao_bao_nnu_d.txt
pyfisher/data/v20201120_boss_bao/v20201120_boss_bao_bao_nnu_u.txt
pyfisher/data/v20201120_boss_bao/v20201120_boss_bao_bao_ok_d.txt
pyfisher/data/v20201120_boss_bao/v20201120_boss_bao_bao_ok_u.txt
pyfisher/data/v20201120_boss_bao/v20201120_boss_bao_bao_ombh2_d.txt
pyfisher/data/v20201120_boss_bao/v20201120_boss_bao_bao_ombh2_u.txt
pyfisher/data/v20201120_boss_bao/v20201120_boss_bao_bao_omch2_d.txt
pyfisher/data/v20201120_boss_bao/v20201120_boss_bao_bao_omch2_u.txt
pyfisher/data/v20201120_boss_bao/v20201120_boss_bao_bao_w0_d.txt
pyfisher/data/v20201120_boss_bao/v20201120_boss_bao_bao_w0_u.txt
pyfisher/data/v20201120_boss_bao/v20201120_boss_bao_bao_wa_d.txt
pyfisher/data/v20201120_boss_bao/v20201120_boss_bao_bao_wa_u.txt
pyfisher/data/v20201120_cmb_derivs/params.txt
pyfisher/data/v20201120_cmb_derivs/v20201120_cmb_derivs_cmb_As_d.txt
pyfisher/data/v20201120_cmb_derivs/v20201120_cmb_derivs_cmb_As_deriv.txt
pyfisher/data/v20201120_cmb_derivs/v20201120_cmb_derivs_cmb_As_u.txt
pyfisher/data/v20201120_cmb_derivs/v20201120_cmb_derivs_cmb_H0_d.txt
pyfisher/data/v20201120_cmb_derivs/v20201120_cmb_derivs_cmb_H0_deriv.txt
pyfisher/data/v20201120_cmb_derivs/v20201120_cmb_derivs_cmb_H0_u.txt
pyfisher-2.1.0.dist-info/AUTHORS.rst
pyfisher-2.1.0.dist-info/LICENSE
pyfisher-2.1.0.dist-info/METADATA
pyfisher-2.1.0.dist-info/WHEEL
pyfisher-2.1.0.dist-info/top_level.txt
pyfisher-2.1.0.dist-info/RECORD
