Metadata-Version: 2.1
Name: pyfisher
Version: 2.1.0
Summary: Fisher forecasting for cosmological surveys
Home-page: https://github.com/msyriac/pyfisher
Author: Mathew Madhavacheril
Author-email: mathewsyriac@gmail.com
License: BSD license
Keywords: pyfisher
Platform: UNKNOWN
Classifier: Development Status :: 2 - Pre-Alpha
Classifier: Intended Audience :: Developers
Classifier: License :: OSI Approved :: BSD License
Classifier: Natural Language :: English
Classifier: Programming Language :: Python :: 3
Classifier: Programming Language :: Python :: 3.5
Classifier: Programming Language :: Python :: 3.6
Classifier: Programming Language :: Python :: 3.7
Classifier: Programming Language :: Python :: 3.8
Requires-Python: >=3.6
Requires-Dist: numpy
Requires-Dist: matplotlib
Requires-Dist: scipy
Requires-Dist: pandas
Requires-Dist: camb
Requires-Dist: chainconsumer
